fathom_extractor/__init__.py
fathom_extractor/cli.py
fathom_extractor/extractor.py
fathom_extractor-1.0.0.dist-info/licenses/LICENSE
fathom_extractor-1.0.0.dist-info/METADATA
fathom_extractor-1.0.0.dist-info/WHEEL
fathom_extractor-1.0.0.dist-info/entry_points.txt
fathom_extractor-1.0.0.dist-info/top_level.txt
fathom_extractor-1.0.0.dist-info/RECORD
