Metadata-Version: 2.4
Name: fathom-extractor
Version: 1.0.0
Summary: Extract transcripts from HAR files, particularly from Fathom video calls
Author-email: Isaac Harrison Gutekunst <isaac@gutekunst.com>
Maintainer-email: Isaac Harrison Gutekunst <isaac@gutekunst.com>
License: MIT
Project-URL: Homepage, https://github.com/igutekunst/fathom-extractor
Project-URL: Repository, https://github.com/igutekunst/fathom-extractor
Project-URL: Issues, https://github.com/igutekunst/fathom-extractor/issues
Keywords: har,transcript,fathom,extraction,video,audio
Classifier: Development Status :: 4 - Beta
Classifier: Intended Audience :: Developers
Classifier: License :: OSI Approved :: MIT License
Classifier: Operating System :: OS Independent
Classifier: Programming Language :: Python :: 3
Classifier: Programming Language :: Python :: 3.8
Classifier: Programming Language :: Python :: 3.9
Classifier: Programming Language :: Python :: 3.10
Classifier: Programming Language :: Python :: 3.11
Classifier: Programming Language :: Python :: 3.12
Classifier: Topic :: Internet :: WWW/HTTP
Classifier: Topic :: Multimedia :: Sound/Audio :: Speech
Classifier: Topic :: Text Processing :: Linguistic
Classifier: Topic :: Utilities
Requires-Python: >=3.8
License-File: LICENSE
Provides-Extra: dev
Requires-Dist: pytest>=7.0; extra == "dev"
Requires-Dist: black>=22.0; extra == "dev"
Requires-Dist: flake8>=4.0; extra == "dev"
Requires-Dist: mypy>=0.950; extra == "dev"
Dynamic: license-file
